{
    "kind": "osdu:wks:Manifest:1.0.0",
    "ReferenceData": [],
    "MasterData": [],
    "Data": {
        "WorkProduct": {
            "kind": "osdu:wks:work-product--WorkProduct:1.0.0",
            "acl": {
                "owners": [],
                "viewers": []
            },
            "legal": {
                "legaltags": [],
                "otherRelevantDataCountries": []
            },
            "data": {
                "ResourceSecurityClassification": "osdu:reference-data--ResourceSecurityClassification:RESTRICTED:",
                "Name": "1184.csv",
                "Description": "Wellbore Marker",
                "Components": [
                    "surrogate-key:wpc-1"
                ]
            }
        },
        "WorkProductComponents": [
            {
                "id": "surrogate-key:wpc-1",
                "kind": "osdu:wks:work-product-component--WellboreMarkerSet:1.0.0",
                "acl": {
                    "owners": [],
                    "viewers": []
                },
                "legal": {
                    "legaltags": [],
                    "otherRelevantDataCountries": []
                },
                "meta": [
                    {
                        "kind": "Unit",
                        "name": "m",
                        "persistableReference": "",
                        "unitOfMeasureID": "osdu:reference-data--UnitOfMeasure:m:",
                        "propertyNames": [
                            "Markers[].MarkerMeasuredDepth"
                        ]
                    }
                ],
                "data": {
                    "ResourceSecurityClassification": "osdu:reference-data--ResourceSecurityClassification:RESTRICTED:",
                    "Name": "1184.csv",
                    "Description": "Wellbore Marker",
                    "Datasets": [
                        "surrogate-key:file-1"
                    ],
                    "WellboreID": "osdu:master-data--Wellbore:1184:",
                    "Markers": [
                        {
                            "MarkerName": "North Sea Supergroup",
                            "MarkerMeasuredDepth": 0.0
                        },
                        {
                            "MarkerName": "Ommelanden Formation",
                            "MarkerMeasuredDepth": 508.0
                        },
                        {
                            "MarkerName": "Texel Formation",
                            "MarkerMeasuredDepth": 1249.5
                        },
                        {
                            "MarkerName": "Upper Holland Marl Member",
                            "MarkerMeasuredDepth": 1363.0
                        },
                        {
                            "MarkerName": "Middle Holland Claystone Member",
                            "MarkerMeasuredDepth": 1460.0
                        },
                        {
                            "MarkerName": "Middle Muschelkalk Marl Member",
                            "MarkerMeasuredDepth": 1468.0
                        },
                        {
                            "MarkerName": "Lower Muschelkalk Member",
                            "MarkerMeasuredDepth": 1475.0
                        },
                        {
                            "MarkerName": "Upper R\u00f6t Claystone Member",
                            "MarkerMeasuredDepth": 1583.0
                        },
                        {
                            "MarkerName": "Upper R\u00f6t Evaporite Member",
                            "MarkerMeasuredDepth": 1683.0
                        },
                        {
                            "MarkerName": "Intermediate R\u00f6t Claystone Member",
                            "MarkerMeasuredDepth": 1689.0
                        },
                        {
                            "MarkerName": "Main R\u00f6t Evaporite Member",
                            "MarkerMeasuredDepth": 1710.0
                        },
                        {
                            "MarkerName": "Solling Claystone Member",
                            "MarkerMeasuredDepth": 1804.0
                        },
                        {
                            "MarkerName": "Basal Solling Sandstone Member",
                            "MarkerMeasuredDepth": 1908.0
                        },
                        {
                            "MarkerName": "Volpriehausen Clay-Siltstone Member",
                            "MarkerMeasuredDepth": 1911.0
                        },
                        {
                            "MarkerName": "Lower Volpriehausen Sandstone Member",
                            "MarkerMeasuredDepth": 1986.5
                        },
                        {
                            "MarkerName": "Rogenstein Member",
                            "MarkerMeasuredDepth": 2001.0
                        },
                        {
                            "MarkerName": "Main Claystone Member",
                            "MarkerMeasuredDepth": 2175.0
                        },
                        {
                            "MarkerName": "Zechstein Upper Claystone Formation",
                            "MarkerMeasuredDepth": 2375.0
                        },
                        {
                            "MarkerName": "Z4 Salt Member",
                            "MarkerMeasuredDepth": 2411.0
                        },
                        {
                            "MarkerName": "Z4 Pegmatite Anhydrite Member",
                            "MarkerMeasuredDepth": 2431.5
                        },
                        {
                            "MarkerName": "Red Salt Clay Member",
                            "MarkerMeasuredDepth": 2435.5
                        },
                        {
                            "MarkerName": "Lower Zechstein salt",
                            "MarkerMeasuredDepth": 2445.0
                        },
                        {
                            "MarkerName": "Z2 Basal Anhydrite Member",
                            "MarkerMeasuredDepth": 2936.0
                        },
                        {
                            "MarkerName": "Z2 Carbonate Member",
                            "MarkerMeasuredDepth": 2938.5
                        },
                        {
                            "MarkerName": "Z1 Anhydrite Member",
                            "MarkerMeasuredDepth": 2982.5
                        },
                        {
                            "MarkerName": "Z1 Carbonate Member",
                            "MarkerMeasuredDepth": 3029.0
                        },
                        {
                            "MarkerName": "Coppershale Member",
                            "MarkerMeasuredDepth": 3030.5
                        },
                        {
                            "MarkerName": "Tubbergen Formation",
                            "MarkerMeasuredDepth": 3031.0
                        }
                    ]
                }
            }
        ],
        "Datasets": [
            {
                "id": "surrogate-key:file-1",
                "kind": "osdu:wks:dataset--File.Generic:1.0.0",
                "acl": {
                    "owners": [],
                    "viewers": []
                },
                "legal": {
                    "legaltags": [],
                    "otherRelevantDataCountries": []
                },
                "data": {
                    "ResourceSecurityClassification": "osdu:reference-data--ResourceSecurityClassification:RESTRICTED:",
                    "SchemaFormatTypeID": "osdu:reference-data--SchemaFormatType:TabSeparatedColumnarText:",
                    "DatasetProperties": {
                        "FileSourceInfo": {
                            "FileSource": "s3://osdu-seismic-test-data/r1/data/provided/markers/1184.csv",
                            "Name": "1184.csv",
                            "PreloadFilePath": "s3://osdu-seismic-test-data/r1/data/provided/markers/1184.csv"
                        }
                    }
                }
            }
        ]
    }
}