{
    "kind": "osdu:wks:Manifest:1.0.0",
    "ReferenceData": [],
    "MasterData": [],
    "Data": {
        "WorkProduct": {
            "kind": "osdu:wks:work-product--WorkProduct:1.0.0",
            "acl": {
                "owners": [],
                "viewers": []
            },
            "legal": {
                "legaltags": [],
                "otherRelevantDataCountries": []
            },
            "data": {
                "ResourceSecurityClassification": "osdu:reference-data--ResourceSecurityClassification:RESTRICTED:",
                "Name": "7147.csv",
                "Description": "Wellbore Marker",
                "Components": [
                    "surrogate-key:wpc-1"
                ]
            }
        },
        "WorkProductComponents": [
            {
                "id": "surrogate-key:wpc-1",
                "kind": "osdu:wks:work-product-component--WellboreMarkerSet:1.0.0",
                "acl": {
                    "owners": [],
                    "viewers": []
                },
                "legal": {
                    "legaltags": [],
                    "otherRelevantDataCountries": []
                },
                "meta": [
                    {
                        "kind": "Unit",
                        "name": "m",
                        "persistableReference": "",
                        "unitOfMeasureID": "osdu:reference-data--UnitOfMeasure:m:",
                        "propertyNames": [
                            "Markers[].MarkerMeasuredDepth"
                        ]
                    }
                ],
                "data": {
                    "ResourceSecurityClassification": "osdu:reference-data--ResourceSecurityClassification:RESTRICTED:",
                    "Name": "7147.csv",
                    "Description": "Wellbore Marker",
                    "Datasets": [
                        "surrogate-key:file-1"
                    ],
                    "WellboreID": "osdu:master-data--Wellbore:7147:",
                    "Markers": [
                        {
                            "MarkerName": "Upper North Sea Group",
                            "MarkerMeasuredDepth": 0.0
                        },
                        {
                            "MarkerName": "Rupel Clay Member",
                            "MarkerMeasuredDepth": 420.0
                        },
                        {
                            "MarkerName": "Dongen Clay Member",
                            "MarkerMeasuredDepth": 455.0
                        },
                        {
                            "MarkerName": "Basal Dongen Tuffite Member",
                            "MarkerMeasuredDepth": 689.0
                        },
                        {
                            "MarkerName": "Landen Clay Member",
                            "MarkerMeasuredDepth": 701.0
                        },
                        {
                            "MarkerName": "Ommelanden Formation",
                            "MarkerMeasuredDepth": 721.0
                        },
                        {
                            "MarkerName": "Vlieland Claystone Formation",
                            "MarkerMeasuredDepth": 885.0
                        },
                        {
                            "MarkerName": "R\u00f6t Claystone Member",
                            "MarkerMeasuredDepth": 920.0
                        },
                        {
                            "MarkerName": "Main R\u00f6t Evaporite Member",
                            "MarkerMeasuredDepth": 935.0
                        },
                        {
                            "MarkerName": "Solling Claystone Member",
                            "MarkerMeasuredDepth": 941.5
                        },
                        {
                            "MarkerName": "Basal Solling Sandstone Member",
                            "MarkerMeasuredDepth": 947.0
                        },
                        {
                            "MarkerName": "Lower Detfurth Sandstone Member",
                            "MarkerMeasuredDepth": 950.0
                        },
                        {
                            "MarkerName": "Volpriehausen Clay-Siltstone Member",
                            "MarkerMeasuredDepth": 970.5
                        },
                        {
                            "MarkerName": "Lower Volpriehausen Sandstone Member",
                            "MarkerMeasuredDepth": 1020.5
                        },
                        {
                            "MarkerName": "Rogenstein Member",
                            "MarkerMeasuredDepth": 1105.0
                        },
                        {
                            "MarkerName": "Main Claystone Member",
                            "MarkerMeasuredDepth": 1275.0
                        },
                        {
                            "MarkerName": "Zechstein Upper Claystone Formation",
                            "MarkerMeasuredDepth": 1442.5
                        },
                        {
                            "MarkerName": "Upper Zechstein salt",
                            "MarkerMeasuredDepth": 1455.5
                        },
                        {
                            "MarkerName": "Z3 Main Anhydrite Member",
                            "MarkerMeasuredDepth": 1816.0
                        },
                        {
                            "MarkerName": "Z3 Carbonate Member",
                            "MarkerMeasuredDepth": 1831.0
                        },
                        {
                            "MarkerName": "Grey Salt Clay Member",
                            "MarkerMeasuredDepth": 1839.0
                        },
                        {
                            "MarkerName": "Z2 Salt Member",
                            "MarkerMeasuredDepth": 1840.5
                        },
                        {
                            "MarkerName": "Z2 Basal Anhydrite Member",
                            "MarkerMeasuredDepth": 3208.0
                        },
                        {
                            "MarkerName": "Z2 Carbonate Member",
                            "MarkerMeasuredDepth": 3211.5
                        },
                        {
                            "MarkerName": "Z1 Lower Anhydrite Member",
                            "MarkerMeasuredDepth": 3222.5
                        },
                        {
                            "MarkerName": "Z1 Carbonate Member",
                            "MarkerMeasuredDepth": 3241.0
                        },
                        {
                            "MarkerName": "Coppershale Member",
                            "MarkerMeasuredDepth": 3252.0
                        },
                        {
                            "MarkerName": "Ten Boer Member",
                            "MarkerMeasuredDepth": 3253.0
                        },
                        {
                            "MarkerName": "Upper Slochteren Member",
                            "MarkerMeasuredDepth": 3268.0
                        },
                        {
                            "MarkerName": "Ameland Member",
                            "MarkerMeasuredDepth": 3383.0
                        },
                        {
                            "MarkerName": "Lower Slochteren Member",
                            "MarkerMeasuredDepth": 3393.0
                        },
                        {
                            "MarkerName": "Limburg Groep",
                            "MarkerMeasuredDepth": 3487.0
                        }
                    ]
                }
            }
        ],
        "Datasets": [
            {
                "id": "surrogate-key:file-1",
                "kind": "osdu:wks:dataset--File.Generic:1.0.0",
                "acl": {
                    "owners": [],
                    "viewers": []
                },
                "legal": {
                    "legaltags": [],
                    "otherRelevantDataCountries": []
                },
                "data": {
                    "ResourceSecurityClassification": "osdu:reference-data--ResourceSecurityClassification:RESTRICTED:",
                    "SchemaFormatTypeID": "osdu:reference-data--SchemaFormatType:TabSeparatedColumnarText:",
                    "DatasetProperties": {
                        "FileSourceInfo": {
                            "FileSource": "s3://osdu-seismic-test-data/r1/data/provided/markers/7147.csv",
                            "Name": "7147.csv",
                            "PreloadFilePath": "s3://osdu-seismic-test-data/r1/data/provided/markers/7147.csv"
                        }
                    }
                }
            }
        ]
    }
}