{
    "kind": "osdu:wks:Manifest:1.0.0",
    "ReferenceData": [],
    "MasterData": [],
    "Data": {
        "WorkProduct": {
            "kind": "osdu:wks:work-product--WorkProduct:1.0.0",
            "acl": {
                "owners": [],
                "viewers": []
            },
            "legal": {
                "legaltags": [],
                "otherRelevantDataCountries": []
            },
            "data": {
                "ResourceSecurityClassification": "osdu:reference-data--ResourceSecurityClassification:RESTRICTED:",
                "Name": "4162.csv",
                "Description": "Wellbore Marker",
                "Components": [
                    "surrogate-key:wpc-1"
                ]
            }
        },
        "WorkProductComponents": [
            {
                "id": "surrogate-key:wpc-1",
                "kind": "osdu:wks:work-product-component--WellboreMarkerSet:1.0.0",
                "acl": {
                    "owners": [],
                    "viewers": []
                },
                "legal": {
                    "legaltags": [],
                    "otherRelevantDataCountries": []
                },
                "meta": [
                    {
                        "kind": "Unit",
                        "name": "m",
                        "persistableReference": "",
                        "unitOfMeasureID": "osdu:reference-data--UnitOfMeasure:m:",
                        "propertyNames": [
                            "Markers[].MarkerMeasuredDepth"
                        ]
                    }
                ],
                "data": {
                    "ResourceSecurityClassification": "osdu:reference-data--ResourceSecurityClassification:RESTRICTED:",
                    "Name": "4162.csv",
                    "Description": "Wellbore Marker",
                    "Datasets": [
                        "surrogate-key:file-1"
                    ],
                    "WellboreID": "osdu:master-data--Wellbore:4162:",
                    "Markers": [
                        {
                            "MarkerName": "North Sea Supergroup",
                            "MarkerMeasuredDepth": 0.0
                        },
                        {
                            "MarkerName": "Chalk Group",
                            "MarkerMeasuredDepth": 778.0
                        },
                        {
                            "MarkerName": "Holland Formation",
                            "MarkerMeasuredDepth": 1875.0
                        },
                        {
                            "MarkerName": "Vlieland Claystone Formation",
                            "MarkerMeasuredDepth": 1920.0
                        },
                        {
                            "MarkerName": "Rogenstein Member",
                            "MarkerMeasuredDepth": 1942.0
                        },
                        {
                            "MarkerName": "Main Claystone Member",
                            "MarkerMeasuredDepth": 2005.0
                        },
                        {
                            "MarkerName": "Lower Buntsandstein Formation",
                            "MarkerMeasuredDepth": 2225.0
                        },
                        {
                            "MarkerName": "Z4 Salt Member",
                            "MarkerMeasuredDepth": 2250.0
                        },
                        {
                            "MarkerName": "Z4 Pegmatite Anhydrite Member",
                            "MarkerMeasuredDepth": 2285.0
                        },
                        {
                            "MarkerName": "Red Salt Clay Member",
                            "MarkerMeasuredDepth": 2287.0
                        },
                        {
                            "MarkerName": "Z3 Salt Member",
                            "MarkerMeasuredDepth": 2291.0
                        },
                        {
                            "MarkerName": "Z3 Main Anhydrite Member",
                            "MarkerMeasuredDepth": 2485.0
                        },
                        {
                            "MarkerName": "Z3 Carbonate Member",
                            "MarkerMeasuredDepth": 2517.0
                        },
                        {
                            "MarkerName": "Grey Salt Clay Member",
                            "MarkerMeasuredDepth": 2521.0
                        },
                        {
                            "MarkerName": "Z2 Roof Anhydrite Member",
                            "MarkerMeasuredDepth": 2522.0
                        },
                        {
                            "MarkerName": "Z2 Salt Member",
                            "MarkerMeasuredDepth": 2523.0
                        },
                        {
                            "MarkerName": "Z2 Basal Anhydrite Member",
                            "MarkerMeasuredDepth": 2978.0
                        },
                        {
                            "MarkerName": "Z2 Carbonate Member",
                            "MarkerMeasuredDepth": 2982.0
                        },
                        {
                            "MarkerName": "Z1 Anhydrite Member",
                            "MarkerMeasuredDepth": 3007.0
                        },
                        {
                            "MarkerName": "Z1 Carbonate Member",
                            "MarkerMeasuredDepth": 3066.0
                        },
                        {
                            "MarkerName": "Coppershale Member",
                            "MarkerMeasuredDepth": 3078.0
                        },
                        {
                            "MarkerName": "Slochteren Formation",
                            "MarkerMeasuredDepth": 3079.0
                        }
                    ]
                }
            }
        ],
        "Datasets": [
            {
                "id": "surrogate-key:file-1",
                "kind": "osdu:wks:dataset--File.Generic:1.0.0",
                "acl": {
                    "owners": [],
                    "viewers": []
                },
                "legal": {
                    "legaltags": [],
                    "otherRelevantDataCountries": []
                },
                "data": {
                    "ResourceSecurityClassification": "osdu:reference-data--ResourceSecurityClassification:RESTRICTED:",
                    "SchemaFormatTypeID": "osdu:reference-data--SchemaFormatType:TabSeparatedColumnarText:",
                    "DatasetProperties": {
                        "FileSourceInfo": {
                            "FileSource": "s3://osdu-seismic-test-data/r1/data/provided/markers/4162.csv",
                            "Name": "4162.csv",
                            "PreloadFilePath": "s3://osdu-seismic-test-data/r1/data/provided/markers/4162.csv"
                        }
                    }
                }
            }
        ]
    }
}